austin/__init__.py
austin/aio.py
austin/base.py
austin/cli.py
austin/config.py
austin/errors.py
austin/events.py
austin/simple.py
austin/stats.py
austin/threads.py
austin/format/__init__.py
austin/format/collapsed_stack.py
austin/format/compress.py
austin/format/mojo.py
austin/format/speedscope.py
austin/format/pprof/__init__.py
austin/format/pprof/__main__.py
austin/format/pprof/profile.proto
austin/format/pprof/profile_pb2.py
austin/tools/diff.py
austin/tools/mojodbg.py
austin/tools/resolve.py
austin_python-2.1.2.dist-info/METADATA
austin_python-2.1.2.dist-info/WHEEL
austin_python-2.1.2.dist-info/entry_points.txt
austin_python-2.1.2.dist-info/licenses/AUTHORS
austin_python-2.1.2.dist-info/licenses/COPYING
austin_python-2.1.2.dist-info/licenses/LICENSE.md
austin_python-2.1.2.dist-info/RECORD
