Metadata-Version: 2.4
Name: austin-python
Version: 2.1.2
Summary: Python wrapper for Austin, the CPython frame stack sampler.
Project-URL: homepage, https://github.com/P403n1x87/austin-python
Project-URL: documentation, https://austin-python.readthedocs.io
Project-URL: repository, https://github.com/P403n1x87/austin-python
Project-URL: issues, https://github.com/P403n1x87/austin-python/issues
Author-email: "Gabriele N. Tornetta" <phoenix1987@gmail.com>
License-Expression: GPL-3.0-or-later
License-File: AUTHORS
License-File: COPYING
License-File: LICENSE.md
Keywords: development,performance,profiling,testing
Classifier: Development Status :: 5 - Production/Stable
Classifier: Intended Audience :: Developers
Classifier: License :: OSI Approved :: GNU General Public License v3 or later (GPLv3+)
Classifier: Programming Language :: Python :: 3.9
Classifier: Programming Language :: Python :: 3.10
Classifier: Programming Language :: Python :: 3.11
Classifier: Programming Language :: Python :: 3.12
Classifier: Programming Language :: Python :: 3.13
Requires-Python: >=3.9
Requires-Dist: protobuf~=3.12
Requires-Dist: psutil>=5.7.0
Requires-Dist: toml~=0.10
